poetry_legacy_index/__init__.py
poetry_legacy_index/main.py
poetry_legacy_index-1.2.0.dist-info/METADATA
poetry_legacy_index-1.2.0.dist-info/WHEEL
poetry_legacy_index-1.2.0.dist-info/entry_points.txt
poetry_legacy_index-1.2.0.dist-info/RECORD
