Metadata-Version: 2.1
Name: poetry-legacy-index
Version: 1.2.0
Summary: 
Author: Maz Jaleel
Author-email: mazjaleel@gmail.com
Requires-Python: >=3.7,<4.0
Classifier: Programming Language :: Python :: 3
Classifier: Programming Language :: Python :: 3.7
Classifier: Programming Language :: Python :: 3.8
Classifier: Programming Language :: Python :: 3.9
Classifier: Programming Language :: Python :: 3.10
Classifier: Programming Language :: Python :: 3.11
Requires-Dist: poetry (>=1.4.1,<2.0.0)
